rcapi/__init__.py
rcapi/cli.py
rcapi/version.py
rackcorp_api_client-0.0.4.dist-info/LICENSE
rackcorp_api_client-0.0.4.dist-info/METADATA
rackcorp_api_client-0.0.4.dist-info/WHEEL
rackcorp_api_client-0.0.4.dist-info/entry_points.txt
rackcorp_api_client-0.0.4.dist-info/top_level.txt
rackcorp_api_client-0.0.4.dist-info/RECORD
